README.txt
setup.py
cs/__init__.py
cs.bodysection.egg-info/PKG-INFO
cs.bodysection.egg-info/SOURCES.txt
cs.bodysection.egg-info/dependency_links.txt
cs.bodysection.egg-info/entry_points.txt
cs.bodysection.egg-info/namespace_packages.txt
cs.bodysection.egg-info/not-zip-safe
cs.bodysection.egg-info/paster_plugins.txt
cs.bodysection.egg-info/requires.txt
cs.bodysection.egg-info/top_level.txt
cs/bodysection/__init__.py
cs/bodysection/configure.zcml
cs/bodysection/navigation.py
cs/bodysection/tests.py
docs/HISTORY.txt
docs/INSTALL.txt
docs/LICENSE.GPL
docs/LICENSE.txt