Metadata-Version: 1.1
Name: cs.bodysection
Version: 1.3
Summary: Extra view to add section name for Plone. Specially useful when having INavigationRoot based sites (like ones with LinguaPlone
Home-page: http://code.codesyntax.com/private/cs.bodysection
Author: Mikel Larreategi
Author-email: mlarreategi@codesyntax.com
License: GPL
Platform: UNKNOWN
Classifier: Framework :: Plone
Classifier: Programming Language :: Python
